questions/__init__.py
questions/cli.py
questions/form.py
questions/questions.py
questions/settings.py
questions/templates.py
questions/utils.py
questions/validators.py
questions/templates/survey_html.angular.jinja
questions/templates/survey_html.jquery.jinja
questions/templates/survey_html.ko.jinja
questions/templates/survey_html.react.jinja
questions/templates/survey_html.vue.jinja
questions/templates/survey_js.angular.jinja
questions/templates/survey_js.jquery.jinja
questions/templates/survey_js.ko.jinja
questions/templates/survey_js.react.jinja
questions/templates/survey_js.vue.jinja
questions-0.8.0.dist-info/AUTHORS.rst
questions-0.8.0.dist-info/LICENSE
questions-0.8.0.dist-info/METADATA
questions-0.8.0.dist-info/WHEEL
questions-0.8.0.dist-info/entry_points.txt
questions-0.8.0.dist-info/top_level.txt
questions-0.8.0.dist-info/RECORD
