Metadata-Version: 2.1
Name: questions
Version: 0.8.0
Summary: Questions is a form library that uses the power of SurveyJS for the UI.
Home-page: https://github.com/cguardia/questions
Author: Carlos de la Guardia
Author-email: cguardia@yahoo.com
License: MIT license
Keywords: questions
Classifier: Development Status :: 3 - Alpha
Classifier: Intended Audience :: Developers
Classifier: License :: OSI Approved :: MIT License
Classifier: Natural Language :: English
Classifier: Programming Language :: Python :: 3
Classifier: Programming Language :: Python :: 3.8
Classifier: Programming Language :: Python :: 3.9
Classifier: Topic :: Internet :: WWW/HTTP
Classifier: Topic :: Internet :: WWW/HTTP :: Dynamic Content
Classifier: Topic :: Software Development :: Libraries :: Python Modules
Requires-Python: >=3.8
License-File: LICENSE
License-File: AUTHORS.rst
Requires-Dist: Click (>=7.0)
Requires-Dist: email-validator
Requires-Dist: Jinja2
Requires-Dist: pydantic
Requires-Dist: requests
Requires-Dist: simpleeval
